{
    "dashboard": {
        "states": [
            {
                "label": "{{lightingMode.value}}",
                "alternatives": [
                    {
                        "key": "reading",
                        "value": "Reading",
                        "type": "active",
                        "description": "4000K natural light for comfortable reading."
                    },
                    {
                        "key": "writing",
                        "value": "Writing",
                        "type": "active",
                        "description": "5000K white light that makes it easy to focus on your work."
                    },
                    {
                        "key": "computer",
                        "value": "Computer",
                        "type": "active",
                        "description": "Backlight only to help you immerse yourself in movies and games."
                    },
                    {
                        "key": "day",
                        "value": "Daylight",
                        "type": "active",
                        "description": "Energising light that's similar to sunlight."
                    },
                    {
                        "key": "night",
                        "value": "Night",
                        "type": "active",
                        "description": "Dim the light to help you relax."
                    },
                    {
                        "key": "sleepPreparation",
                        "value": "Sleep",
                        "type": "active",
                        "description": "Get a breathing guide to help you relax and fall asleep. Breathe in for 4 seconds as the light gets brighter, hold your breath for 7 seconds when the light is steady, and breathe out for 8 seconds as the light gets darker. The light will turn off after 4 breaths."
                    },
                    {
                        "key": "cozy",
                        "value": "Cosy",
                        "type": "active",
                        "description": "Warm light to make you feel comfortable."
                    },
                    {
                        "key": "soft",
                        "value": "Soft",
                        "type": "active",
                        "description": "Gentle light to set the mood."
                    }
                ]
            }
        ],
        "actions": [],
        "panelItems": []
    },
    "detailView": [
        {
            "label": "Light mode",
            "displayType": "list",
            "list": {
                "command": {
                    "name": "setLightingMode",
                    "alternatives": [
                        {
                            "key": "reading",
                            "value": "Reading",
                            "type": "active",
                            "description": "4000K natural light for comfortable reading."
                        },
                        {
                            "key": "writing",
                            "value": "Writing",
                            "type": "active",
                            "description": "5000K white light that makes it easy to focus on your work."
                        },
                        {
                            "key": "computer",
                            "value": "Computer",
                            "type": "active",
                            "description": "Backlight only to help you immerse yourself in movies and games."
                        },
                        {
                            "key": "day",
                            "value": "Daylight",
                            "type": "active",
                            "description": "Energising light that's similar to sunlight."
                        },
                        {
                            "key": "night",
                            "value": "Night",
                            "type": "active",
                            "description": "Dim the light to help you relax."
                        },
                        {
                            "key": "sleepPreparation",
                            "value": "Sleep",
                            "type": "active",
                            "description": "Get a breathing guide to help you relax and fall asleep. Breathe in for 4 seconds as the light gets brighter, hold your breath for 7 seconds when the light is steady, and breathe out for 8 seconds as the light gets darker. The light will turn off after 4 breaths."
                        },
                        {
                            "key": "cozy",
                            "value": "Cosy",
                            "type": "active",
                            "description": "Warm light to make you feel comfortable."
                        },
                        {
                            "key": "soft",
                            "value": "Soft",
                            "type": "active",
                            "description": "Gentle light to set the mood."
                        }
                    ]
                },
                "state": {
                    "value": "lightingMode.value",
                    "alternatives": [
                        {
                            "key": "reading",
                            "value": "Reading",
                            "type": "active",
                            "description": "4000K natural light for comfortable reading."
                        },
                        {
                            "key": "writing",
                            "value": "Writing",
                            "type": "active",
                            "description": "5000K white light that makes it easy to focus on your work."
                        },
                        {
                            "key": "computer",
                            "value": "Computer",
                            "type": "active",
                            "description": "Backlight only to help you immerse yourself in movies and games."
                        },
                        {
                            "key": "day",
                            "value": "Daylight",
                            "type": "active",
                            "description": "Energising light that's similar to sunlight."
                        },
                        {
                            "key": "night",
                            "value": "Night",
                            "type": "active",
                            "description": "Dim the light to help you relax."
                        },
                        {
                            "key": "sleepPreparation",
                            "value": "Sleep",
                            "type": "active",
                            "description": "Get a breathing guide to help you relax and fall asleep. Breathe in for 4 seconds as the light gets brighter, hold your breath for 7 seconds when the light is steady, and breathe out for 8 seconds as the light gets darker. The light will turn off after 4 breaths."
                        },
                        {
                            "key": "cozy",
                            "value": "Cosy",
                            "type": "active",
                            "description": "Warm light to make you feel comfortable."
                        },
                        {
                            "key": "soft",
                            "value": "Soft",
                            "type": "active",
                            "description": "Gentle light to set the mood."
                        }
                    ]
                }
            }
        }
    ],
    "automation": {
        "conditions": [
            {
                "label": "Light mode",
                "displayType": "list",
                "list": {
                    "alternatives": [
                        {
                            "key": "reading",
                            "value": "Reading",
                            "type": "active",
                            "description": "4000K natural light for comfortable reading."
                        },
                        {
                            "key": "writing",
                            "value": "Writing",
                            "type": "active",
                            "description": "5000K white light that makes it easy to focus on your work."
                        },
                        {
                            "key": "computer",
                            "value": "Computer",
                            "type": "active",
                            "description": "Backlight only to help you immerse yourself in movies and games."
                        },
                        {
                            "key": "day",
                            "value": "Daylight",
                            "type": "active",
                            "description": "Energising light that's similar to sunlight."
                        },
                        {
                            "key": "night",
                            "value": "Night",
                            "type": "active",
                            "description": "Dim the light to help you relax."
                        },
                        {
                            "key": "sleepPreparation",
                            "value": "Sleep",
                            "type": "active",
                            "description": "Get a breathing guide to help you relax and fall asleep. Breathe in for 4 seconds as the light gets brighter, hold your breath for 7 seconds when the light is steady, and breathe out for 8 seconds as the light gets darker. The light will turn off after 4 breaths."
                        },
                        {
                            "key": "cozy",
                            "value": "Cosy",
                            "type": "active",
                            "description": "Warm light to make you feel comfortable."
                        },
                        {
                            "key": "soft",
                            "value": "Soft",
                            "type": "active",
                            "description": "Gentle light to set the mood."
                        }
                    ],
                    "value": "lightingMode.value",
                    "multiSelectable": false
                }
            }
        ],
        "actions": [
            {
                "label": "Light mode",
                "displayType": "list",
                "list": {
                    "alternatives": [
                        {
                            "key": "reading",
                            "value": "Reading",
                            "type": "active",
                            "description": "4000K natural light for comfortable reading."
                        },
                        {
                            "key": "writing",
                            "value": "Writing",
                            "type": "active",
                            "description": "5000K white light that makes it easy to focus on your work."
                        },
                        {
                            "key": "computer",
                            "value": "Computer",
                            "type": "active",
                            "description": "Backlight only to help you immerse yourself in movies and games."
                        },
                        {
                            "key": "day",
                            "value": "Daylight",
                            "type": "active",
                            "description": "Energising light that's similar to sunlight."
                        },
                        {
                            "key": "night",
                            "value": "Night",
                            "type": "active",
                            "description": "Dim the light to help you relax."
                        },
                        {
                            "key": "sleepPreparation",
                            "value": "Sleep",
                            "type": "active",
                            "description": "Get a breathing guide to help you relax and fall asleep. Breathe in for 4 seconds as the light gets brighter, hold your breath for 7 seconds when the light is steady, and breathe out for 8 seconds as the light gets darker. The light will turn off after 4 breaths."
                        },
                        {
                            "key": "cozy",
                            "value": "Cosy",
                            "type": "active",
                            "description": "Warm light to make you feel comfortable."
                        },
                        {
                            "key": "soft",
                            "value": "Soft",
                            "type": "active",
                            "description": "Gentle light to set the mood."
                        }
                    ],
                    "command": "setLightingMode"
                }
            }
        ]
    },
    "id": "activityLightingMode",
    "version": 1
}