{
    "tag": "fr",
    "label": "Carillon",
    "description": "The Chime capability allows for interacting with devices that serve as a non-alarming attention getter; such as door bells and time-of-day indicators.",
    "attributes": {
        "chime": {
            "label": "Carillon",
            "description": "A string representation of whether the chime is active or off",
            "displayTemplate": "{{device.label}} {{attribute}} was {{value}}",
            "i18n": {
                "value": {
                    "off": {
                        "label": "Désactivé"
                    },
                    "chime": {
                        "label": "Carillon"
                    }
                }
            }
        }
    },
    "commands": {
        "off": {
            "label": "Désactivé",
            "description": "Disable the chime",
            "arguments": {}
        },
        "chime": {
            "label": "Carillon",
            "description": "Enable the chime",
            "arguments": {}
        }
    }
}