{
    "tag": "en",
    "label": "Fan speed",
    "description": "Control fan speed using a percentage value.",
    "attributes": {
        "percent": {
            "label": "Fan speed",
            "description": "The current fan speed represented as a percent value.",
            "displayTemplate": "{{device.label}} {{attribute}} was {{value}}",
            "i18n": []
        }
    },
    "commands": {
        "setPercent": {
            "description": "Set the fan speed percent.",
            "arguments": {
                "percent": {
                    "i18n": [],
                    "description": "The percent value to set the fan speed to."
                }
            }
        }
    }
}