{
    "dashboard": {
        "states": [
            {
                "label": "{{inputSource.value}}",
                "alternatives": [
                    {
                        "key": "AM",
                        "value": "AM",
                        "type": "active"
                    },
                    {
                        "key": "CD",
                        "value": "CD",
                        "type": "active"
                    },
                    {
                        "key": "FM",
                        "value": "FM",
                        "type": "active"
                    },
                    {
                        "key": "HDMI",
                        "value": "HDMI",
                        "type": "active"
                    },
                    {
                        "key": "HDMI1",
                        "value": "HDMI 1",
                        "type": "active"
                    },
                    {
                        "key": "HDMI2",
                        "value": "HDMI 2",
                        "type": "active"
                    },
                    {
                        "key": "HDMI3",
                        "value": "HDMI 3",
                        "type": "active"
                    },
                    {
                        "key": "HDMI4",
                        "value": "HDMI 4",
                        "type": "active"
                    },
                    {
                        "key": "HDMI5",
                        "value": "HDMI 5",
                        "type": "active"
                    },
                    {
                        "key": "HDMI6",
                        "value": "HDMI 6",
                        "type": "active"
                    },
                    {
                        "key": "digitalTv",
                        "value": "Digital TV",
                        "type": "active"
                    },
                    {
                        "key": "USB",
                        "value": "USB",
                        "type": "active"
                    },
                    {
                        "key": "YouTube",
                        "value": "YouTube",
                        "type": "active"
                    },
                    {
                        "key": "aux",
                        "value": "Aux",
                        "type": "active"
                    },
                    {
                        "key": "bluetooth",
                        "value": "Bluetooth",
                        "type": "active"
                    },
                    {
                        "key": "digital",
                        "value": "Digital",
                        "type": "active"
                    },
                    {
                        "key": "melon",
                        "value": "Melon",
                        "type": "active"
                    },
                    {
                        "key": "wifi",
                        "value": "Wi-Fi",
                        "type": "active"
                    },
                    {
                        "key": "network",
                        "value": "Network",
                        "type": "active"
                    },
                    {
                        "key": "optical",
                        "value": "Optical",
                        "type": "active"
                    },
                    {
                        "key": "coaxial",
                        "value": "Coaxial",
                        "type": "active"
                    },
                    {
                        "key": "analog1",
                        "value": "Analogue 1",
                        "type": "active"
                    },
                    {
                        "key": "analog2",
                        "value": "Analogue 2",
                        "type": "active"
                    },
                    {
                        "key": "analog3",
                        "value": "Analogue 3",
                        "type": "active"
                    },
                    {
                        "key": "phono",
                        "value": "Phono",
                        "type": "active"
                    }
                ]
            }
        ],
        "actions": [],
        "panelItems": []
    },
    "detailView": [
        {
            "label": "Media input source",
            "displayType": "list",
            "list": {
                "command": {
                    "name": "setInputSource",
                    "alternatives": [
                        {
                            "key": "AM",
                            "value": "AM",
                            "type": "active"
                        },
                        {
                            "key": "CD",
                            "value": "CD",
                            "type": "active"
                        },
                        {
                            "key": "FM",
                            "value": "FM",
                            "type": "active"
                        },
                        {
                            "key": "HDMI",
                            "value": "HDMI",
                            "type": "active"
                        },
                        {
                            "key": "HDMI1",
                            "value": "HDMI 1",
                            "type": "active"
                        },
                        {
                            "key": "HDMI2",
                            "value": "HDMI 2",
                            "type": "active"
                        },
                        {
                            "key": "HDMI3",
                            "value": "HDMI 3",
                            "type": "active"
                        },
                        {
                            "key": "HDMI4",
                            "value": "HDMI 4",
                            "type": "active"
                        },
                        {
                            "key": "HDMI5",
                            "value": "HDMI 5",
                            "type": "active"
                        },
                        {
                            "key": "HDMI6",
                            "value": "HDMI 6",
                            "type": "active"
                        },
                        {
                            "key": "digitalTv",
                            "value": "Digital TV",
                            "type": "active"
                        },
                        {
                            "key": "USB",
                            "value": "USB",
                            "type": "active"
                        },
                        {
                            "key": "YouTube",
                            "value": "YouTube",
                            "type": "active"
                        },
                        {
                            "key": "aux",
                            "value": "Aux",
                            "type": "active"
                        },
                        {
                            "key": "bluetooth",
                            "value": "Bluetooth",
                            "type": "active"
                        },
                        {
                            "key": "digital",
                            "value": "Digital",
                            "type": "active"
                        },
                        {
                            "key": "melon",
                            "value": "Melon",
                            "type": "active"
                        },
                        {
                            "key": "wifi",
                            "value": "Wi-Fi",
                            "type": "active"
                        },
                        {
                            "key": "network",
                            "value": "Network",
                            "type": "active"
                        },
                        {
                            "key": "optical",
                            "value": "Optical",
                            "type": "active"
                        },
                        {
                            "key": "coaxial",
                            "value": "Coaxial",
                            "type": "active"
                        },
                        {
                            "key": "analog1",
                            "value": "Analogue 1",
                            "type": "active"
                        },
                        {
                            "key": "analog2",
                            "value": "Analogue 2",
                            "type": "active"
                        },
                        {
                            "key": "analog3",
                            "value": "Analogue 3",
                            "type": "active"
                        },
                        {
                            "key": "phono",
                            "value": "Phono",
                            "type": "active"
                        }
                    ],
                    "argumentType": "string",
                    "supportedValues": "supportedInputSources.value"
                },
                "state": {
                    "value": "inputSource.value",
                    "valueType": "string",
                    "alternatives": [
                        {
                            "key": "AM",
                            "value": "AM",
                            "type": "active"
                        },
                        {
                            "key": "CD",
                            "value": "CD",
                            "type": "active"
                        },
                        {
                            "key": "FM",
                            "value": "FM",
                            "type": "active"
                        },
                        {
                            "key": "HDMI",
                            "value": "HDMI",
                            "type": "active"
                        },
                        {
                            "key": "HDMI1",
                            "value": "HDMI 1",
                            "type": "active"
                        },
                        {
                            "key": "HDMI2",
                            "value": "HDMI 2",
                            "type": "active"
                        },
                        {
                            "key": "HDMI3",
                            "value": "HDMI 3",
                            "type": "active"
                        },
                        {
                            "key": "HDMI4",
                            "value": "HDMI 4",
                            "type": "active"
                        },
                        {
                            "key": "HDMI5",
                            "value": "HDMI 5",
                            "type": "active"
                        },
                        {
                            "key": "HDMI6",
                            "value": "HDMI 6",
                            "type": "active"
                        },
                        {
                            "key": "digitalTv",
                            "value": "Digital TV",
                            "type": "active"
                        },
                        {
                            "key": "USB",
                            "value": "USB",
                            "type": "active"
                        },
                        {
                            "key": "YouTube",
                            "value": "YouTube",
                            "type": "active"
                        },
                        {
                            "key": "aux",
                            "value": "Aux",
                            "type": "active"
                        },
                        {
                            "key": "bluetooth",
                            "value": "Bluetooth",
                            "type": "active"
                        },
                        {
                            "key": "digital",
                            "value": "Digital",
                            "type": "active"
                        },
                        {
                            "key": "melon",
                            "value": "Melon",
                            "type": "active"
                        },
                        {
                            "key": "wifi",
                            "value": "Wi-Fi",
                            "type": "active"
                        },
                        {
                            "key": "network",
                            "value": "Network",
                            "type": "active"
                        },
                        {
                            "key": "optical",
                            "value": "Optical",
                            "type": "active"
                        },
                        {
                            "key": "coaxial",
                            "value": "Coaxial",
                            "type": "active"
                        },
                        {
                            "key": "analog1",
                            "value": "Analogue 1",
                            "type": "active"
                        },
                        {
                            "key": "analog2",
                            "value": "Analogue 2",
                            "type": "active"
                        },
                        {
                            "key": "analog3",
                            "value": "Analogue 3",
                            "type": "active"
                        },
                        {
                            "key": "phono",
                            "value": "Phono",
                            "type": "active"
                        }
                    ]
                }
            }
        }
    ],
    "automation": {
        "conditions": [
            {
                "label": "Media input source",
                "displayType": "list",
                "list": {
                    "alternatives": [
                        {
                            "key": "AM",
                            "value": "AM",
                            "type": "active"
                        },
                        {
                            "key": "CD",
                            "value": "CD",
                            "type": "active"
                        },
                        {
                            "key": "FM",
                            "value": "FM",
                            "type": "active"
                        },
                        {
                            "key": "HDMI",
                            "value": "HDMI",
                            "type": "active"
                        },
                        {
                            "key": "HDMI1",
                            "value": "HDMI 1",
                            "type": "active"
                        },
                        {
                            "key": "HDMI2",
                            "value": "HDMI 2",
                            "type": "active"
                        },
                        {
                            "key": "HDMI3",
                            "value": "HDMI 3",
                            "type": "active"
                        },
                        {
                            "key": "HDMI4",
                            "value": "HDMI 4",
                            "type": "active"
                        },
                        {
                            "key": "HDMI5",
                            "value": "HDMI 5",
                            "type": "active"
                        },
                        {
                            "key": "HDMI6",
                            "value": "HDMI 6",
                            "type": "active"
                        },
                        {
                            "key": "digitalTv",
                            "value": "Digital TV",
                            "type": "active"
                        },
                        {
                            "key": "USB",
                            "value": "USB",
                            "type": "active"
                        },
                        {
                            "key": "YouTube",
                            "value": "YouTube",
                            "type": "active"
                        },
                        {
                            "key": "aux",
                            "value": "Aux",
                            "type": "active"
                        },
                        {
                            "key": "bluetooth",
                            "value": "Bluetooth",
                            "type": "active"
                        },
                        {
                            "key": "digital",
                            "value": "Digital",
                            "type": "active"
                        },
                        {
                            "key": "melon",
                            "value": "Melon",
                            "type": "active"
                        },
                        {
                            "key": "wifi",
                            "value": "Wi-Fi",
                            "type": "active"
                        },
                        {
                            "key": "network",
                            "value": "Network",
                            "type": "active"
                        },
                        {
                            "key": "optical",
                            "value": "Optical",
                            "type": "active"
                        },
                        {
                            "key": "coaxial",
                            "value": "Coaxial",
                            "type": "active"
                        },
                        {
                            "key": "analog1",
                            "value": "Analogue 1",
                            "type": "active"
                        },
                        {
                            "key": "analog2",
                            "value": "Analogue 2",
                            "type": "active"
                        },
                        {
                            "key": "analog3",
                            "value": "Analogue 3",
                            "type": "active"
                        },
                        {
                            "key": "phono",
                            "value": "Phono",
                            "type": "active"
                        }
                    ],
                    "supportedValues": "supportedInputSources.value",
                    "value": "inputSource.value",
                    "valueType": "string",
                    "multiSelectable": false
                }
            }
        ],
        "actions": [
            {
                "label": "Media input source",
                "displayType": "list",
                "list": {
                    "alternatives": [
                        {
                            "key": "AM",
                            "value": "AM",
                            "type": "active"
                        },
                        {
                            "key": "CD",
                            "value": "CD",
                            "type": "active"
                        },
                        {
                            "key": "FM",
                            "value": "FM",
                            "type": "active"
                        },
                        {
                            "key": "HDMI",
                            "value": "HDMI",
                            "type": "active"
                        },
                        {
                            "key": "HDMI1",
                            "value": "HDMI 1",
                            "type": "active"
                        },
                        {
                            "key": "HDMI2",
                            "value": "HDMI 2",
                            "type": "active"
                        },
                        {
                            "key": "HDMI3",
                            "value": "HDMI 3",
                            "type": "active"
                        },
                        {
                            "key": "HDMI4",
                            "value": "HDMI 4",
                            "type": "active"
                        },
                        {
                            "key": "HDMI5",
                            "value": "HDMI 5",
                            "type": "active"
                        },
                        {
                            "key": "HDMI6",
                            "value": "HDMI 6",
                            "type": "active"
                        },
                        {
                            "key": "digitalTv",
                            "value": "Digital TV",
                            "type": "active"
                        },
                        {
                            "key": "USB",
                            "value": "USB",
                            "type": "active"
                        },
                        {
                            "key": "YouTube",
                            "value": "YouTube",
                            "type": "active"
                        },
                        {
                            "key": "aux",
                            "value": "Aux",
                            "type": "active"
                        },
                        {
                            "key": "bluetooth",
                            "value": "Bluetooth",
                            "type": "active"
                        },
                        {
                            "key": "digital",
                            "value": "Digital",
                            "type": "active"
                        },
                        {
                            "key": "melon",
                            "value": "Melon",
                            "type": "active"
                        },
                        {
                            "key": "wifi",
                            "value": "Wi-Fi",
                            "type": "active"
                        },
                        {
                            "key": "network",
                            "value": "Network",
                            "type": "active"
                        },
                        {
                            "key": "optical",
                            "value": "Optical",
                            "type": "active"
                        },
                        {
                            "key": "coaxial",
                            "value": "Coaxial",
                            "type": "active"
                        },
                        {
                            "key": "analog1",
                            "value": "Analogue 1",
                            "type": "active"
                        },
                        {
                            "key": "analog2",
                            "value": "Analogue 2",
                            "type": "active"
                        },
                        {
                            "key": "analog3",
                            "value": "Analogue 3",
                            "type": "active"
                        },
                        {
                            "key": "phono",
                            "value": "Phono",
                            "type": "active"
                        }
                    ],
                    "supportedValues": "supportedInputSources.value",
                    "command": "setInputSource",
                    "argumentType": "string"
                }
            }
        ]
    },
    "id": "mediaInputSource",
    "version": 1
}