{
    "tag": "fr",
    "label": "Wattmètre",
    "description": "Allows for reading the power consumption from devices that report it",
    "attributes": {
        "power": {
            "label": "Wattmètre",
            "description": "A number representing the current power consumption. Check the device documentation for how this value is reported",
            "displayTemplate": "{{attribute}} de {{device.label}} est : {{value}} W",
            "i18n": {}
        }
    },
    "commands": {}
}