{
    "tag": "fr",
    "label": "T\u00e9l\u00e9commande",
    "description": "Gets the value of remote control status.",
    "attributes": {
        "remoteControlEnabled": {
            "label": "T\u00e9l\u00e9commande",
            "description": "Current status of the remote control",
            "displayTemplate": "{{attribute}} de {{device.label}} est : {{value}}",
            "i18n": {
                "value": {
                    "false": {
                        "label": "Non autoris\u00e9"
                    },
                    "true": {
                        "label": "Autoris\u00e9"
                    }
                }
            }
        }
    },
    "commands": []
}