{
    "dashboard": {
        "states": [
            {
                "label": "{{doorState.value}}",
                "alternatives": [
                    {
                        "key": "open",
                        "value": "Door open",
                        "type": "active"
                    },
                    {
                        "key": "closed",
                        "value": "Door closed",
                        "type": "active"
                    }
                ]
            }
        ],
        "actions": [],
        "panelItems": []
    },
    "id": "samsungce.doorState",
    "version": 1
}