{
    "dashboard": {
        "states": [
            {
                "label": "{{level.value}} {{level.unit}}"
            }
        ],
        "actions": [],
        "panelItems": [
            {
                "label": "Dimmer",
                "displayType": "slider",
                "slider": {
                    "range": [
                        0,
                        100
                    ],
                    "unit": "level.unit",
                    "command": "setLevel",
                    "argumentType": "integer",
                    "value": "level.value",
                    "valueType": "integer",
                    "availableSizes": [
                        "4x1",
                        "4x2"
                    ]
                }
            }
        ]
    },
    "detailView": [
        {
            "label": "Dimmer",
            "displayType": "slider",
            "slider": {
                "range": [
                    0,
                    100
                ],
                "unit": "level.unit",
                "supportedValues": "levelRange.value",
                "command": "setLevel",
                "argumentType": "integer",
                "value": "level.value",
                "valueType": "integer"
            }
        }
    ],
    "automation": {
        "conditions": [
            {
                "label": "Dimmer",
                "displayType": "slider",
                "slider": {
                    "range": [
                        0,
                        100
                    ],
                    "unit": "level.unit",
                    "supportedValues": "levelRange.value",
                    "value": "level.value",
                    "valueType": "integer"
                }
            }
        ],
        "actions": [
            {
                "label": "Dimmer",
                "displayType": "slider",
                "slider": {
                    "range": [
                        0,
                        100
                    ],
                    "unit": "level.unit",
                    "supportedValues": "levelRange.value",
                    "command": "setLevel",
                    "argumentType": "integer"
                }
            }
        ]
    },
    "id": "switchLevel",
    "version": 1
}